__init__.py
container_manipulations.py
local_storage.py
upload_images.py
q2_label-0.0.1.dist-info/licenses/LICENSE
q2_label-0.0.1.dist-info/METADATA
q2_label-0.0.1.dist-info/WHEEL
q2_label-0.0.1.dist-info/top_level.txt
q2_label-0.0.1.dist-info/RECORD
