Metadata-Version: 2.4
Name: q2_label
Version: 0.0.1
Summary: A package to upload image directory
Author-email: Q2label <q2label@hotmail.com>
License: Copyright (c) 2018 The Python Packaging Authority
Classifier: Programming Language :: Python :: 3
Classifier: Operating System :: OS Independent
Requires-Python: >=3.8
License-File: LICENSE
Requires-Dist: azure-core==1.32.0
Requires-Dist: azure-storage-blob==12.24.0
Dynamic: license-file
